flask_ssl/FlaskSSL.py
flask_ssl/__init__.py
flask_ssl-0.0.0.1rc1.dist-info/LICENSE
flask_ssl-0.0.0.1rc1.dist-info/METADATA
flask_ssl-0.0.0.1rc1.dist-info/WHEEL
flask_ssl-0.0.0.1rc1.dist-info/top_level.txt
flask_ssl-0.0.0.1rc1.dist-info/RECORD
