Metadata-Version: 2.1
Name: flask-ssl
Version: 0.0.0.1rc1
Summary: Flask SSL require and redirect helper decorator
Home-page: https://github.com/standart-ag/flask-ssl
Author: Standart AG, LLC
Author-email: it@standart.lv
License: UNKNOWN
Platform: UNKNOWN
Classifier: Programming Language :: Python :: 3
Classifier: License :: OSI Approved :: MIT License
Classifier: Operating System :: OS Independent
Requires-Dist: flask
